Metadata-Version: 2.1
Name: odoo14-addon-ssi_employee_bank_account_mixin
Version: 14.0.1.2.0
Summary: Employee Bank Account Mixin
Home-page: https://simetri-sinergi.id
Author: PT. Simetri Sinergi Indonesia, OpenSynergy Indonesia
License: AGPL-3
Classifier: Programming Language :: Python
Classifier: Framework :: Odoo
Classifier: Framework :: Odoo :: 14.0
Classifier: License :: OSI Approved :: GNU Affero General Public License v3
Requires-Python: >=3.6
Requires-Dist: odoo14-addon-ssi-employee-document-mixin
Requires-Dist: odoo<14.1dev,>=14.0a
